Metadata-Version: 2.1
Name: efaqa-corpus-zh
Version: 1.2
Summary: Emotional First Aid Dataset, 心理咨询问答语料库
Home-page: https://github.com/chatopera/efaqa-corpus-zh
Author: Hai Liang Wang
Author-email: hain@chatopera.com
License: Chunsong Public License, version 1.0
Keywords: corpus,psychological,machine-learning,deep-learning,NLP,question-answering
Classifier: Intended Audience :: Developers
Classifier: Operating System :: OS Independent
Classifier: Natural Language :: Chinese (Simplified)
Classifier: Natural Language :: Chinese (Traditional)
Classifier: Programming Language :: Python
Classifier: Programming Language :: Python :: 2
Classifier: Programming Language :: Python :: 2.7
Classifier: Programming Language :: Python :: 3
Classifier: Programming Language :: Python :: 3.4
Classifier: Programming Language :: Python :: 3.5
Classifier: Programming Language :: Python :: 3.6
Classifier: Topic :: Text Processing
Classifier: Topic :: Text Processing :: Indexing
Classifier: Topic :: Text Processing :: Linguistic
License-File: LICENSE
